nextag/__main__.py
nextag-1.0.0.dist-info/LICENSE
nextag-1.0.0.dist-info/METADATA
nextag-1.0.0.dist-info/WHEEL
nextag-1.0.0.dist-info/entry_points.txt
nextag-1.0.0.dist-info/top_level.txt
nextag-1.0.0.dist-info/RECORD
